{
  "android.a.a.a" : [ "a", "b", "b$1", "b$a", "b$b", "b$c", "b$d", "b$e" ],
  "android.a.b" : [ "a", "a$a", "a$b", "b", "c", "d", "d$1", "e", "f", "g", "g$a", "g$b", "h", "i", "i$1", "i$a", "j", "k", "l", "m", "m$a", "n" ],
  "android.support.a" : [ "a", "a$a", "a$b" ],
  "android.support.annotation" : [ "Keep" ],
  "android.support.b.a" : [ "a", "b", "c", "c$1", "c$a", "c$b", "d", "e", "e$1", "e$a", "f", "g", "h", "i", "i$a", "i$b", "i$c", "i$d", "i$e", "i$f", "i$g" ],
  "android.support.constraint" : [ "ConstraintLayout", "ConstraintLayout$a", "a", "a$1", "a$a", "b", "c", "c$a" ],
  "android.support.constraint.a" : [ "a", "b", "c", "d", "e", "f", "f$a", "f$b", "g", "g$a" ],
  "android.support.constraint.a.a" : [ "a", "a$1", "a$a", "a$b", "a$c", "b", "b$1", "b$a", "c", "d", "d$1", "e", "f", "g", "g$a", "h" ],
  "android.support.design" : [ "a", "a$a", "a$b", "a$c", "a$d", "a$e", "a$f", "a$g", "a$h", "a$i", "a$j" ],
  "android.support.design.internal" : [ "BaselineLayout", "NavigationMenuItemView", "NavigationMenuItemView$1", "NavigationMenuView", "SnackbarContentLayout", "a" ],
  "android.support.design.widget" : [ "AppBarLayout", "AppBarLayout$Behavior", "AppBarLayout$Behavior$1", "AppBarLayout$Behavior$a", "AppBarLayout$Behavior$b", "AppBarLayout$Behavior$b$1", "AppBarLayout$ScrollingViewBehavior", "AppBarLayout$a", "AppBarLayout$b", "BottomSheetBehavior", "BottomSheetBehavior$1", "BottomSheetBehavior$a", "BottomSheetBehavior$b", "BottomSheetBehavior$b$1", "BottomSheetBehavior$c", "CheckableImageButton", "CheckableImageButton$1", "CoordinatorLayout", "CoordinatorLayout$1", "CoordinatorLayout$a", "CoordinatorLayout$b", "CoordinatorLayout$c", "CoordinatorLayout$d", "CoordinatorLayout$e", "CoordinatorLayout$f", "CoordinatorLayout$f$1", "CoordinatorLayout$g", "FloatingActionButton", "FloatingActionButton$1", "FloatingActionButton$Behavior", "FloatingActionButton$a", "FloatingActionButton$b", "Snackbar", "Snackbar$SnackbarLayout", "SwipeDismissBehavior", "SwipeDismissBehavior$1", "SwipeDismissBehavior$a", "SwipeDismissBehavior$b", "TextInputEditText", "TextInputLayout", "TextInputLayout$1", "TextInputLayout$2", "TextInputLayout$3", "TextInputLayout$4", "TextInputLayout$5", "TextInputLayout$a", "TextInputLayout$a$1", "TextInputLayout$b", "a", "b", "b$1", "b$10", "b$2", "b$3", "b$4", "b$5", "b$6", "b$6$1", "b$7", "b$8", "b$9", "b$a", "b$b", "b$c", "b$d", "b$e", "b$f", "c", "d", "e", "f", "g", "g$1", "g$2", "g$3", "g$a", "g$b", "g$c", "g$d", "g$e", "h", "i", "i$a", "j", "k", "l", "m", "m$1", "m$a", "m$b", "n", "n$1", "n$a", "o", "p", "q", "r", "s", "t", "u" ],
  "android.support.transition" : [ "FragmentTransitionSupport", "FragmentTransitionSupport$1", "FragmentTransitionSupport$2", "FragmentTransitionSupport$3", "FragmentTransitionSupport$4", "a", "aa", "ab", "ac", "ad", "ae", "af", "ag", "ag$1", "ah", "ai", "aj", "aj$a", "ak", "al", "am", "am$1", "am$2", "an", "ao", "ap", "aq", "ar", "as", "at", "at$1", "at$a", "at$b", "au", "av", "aw", "b", "b$a", "c", "d", "e", "f", "f$1", "f$10", "f$2", "f$3", "f$4", "f$5", "f$6", "f$7", "f$8", "f$9", "f$a", "g", "g$1", "g$a", "h", "i", "j", "k", "l", "m", "n", "o", "p", "q", "r", "r$a", "s", "t", "u", "u$1", "u$2", "u$3", "u$a", "u$b", "u$c", "v", "w", "w$a", "w$a$1", "x", "y", "y$1", "y$a", "z" ],
  "android.support.v4.a" : [ "a", "a$1", "a$a", "a$b", "a$c", "a$d", "a$e", "a$e$1", "aa", "ab", "ab$a", "ac", "ac$a", "ac$b", "ac$c", "b", "c", "c$a", "d", "d$1", "e", "f", "g", "g$a", "h", "h$1", "h$2", "h$a", "h$b", "h$c", "h$d", "h$d$1", "i", "i$1", "i$a", "i$b", "j", "k", "l", "m", "m$a", "m$b", "n", "n$1", "n$2", "n$2$1", "n$3", "n$4", "n$a", "n$a$1", "n$b", "n$c", "n$d", "n$e", "n$f", "n$g", "o", "p", "p$1", "q", "q$1", "r", "s", "s$1", "s$2", "s$3", "s$4", "s$a", "t", "t$1", "t$2", "t$3", "t$4", "u", "u$1", "u$2", "u$3", "v", "v$a", "w", "w$a", "x", "y", "z", "z$a" ],
  "android.support.v4.b" : [ "a", "b", "b$a", "b$b", "c" ],
  "android.support.v4.b.a" : [ "a", "a$a", "a$b", "a$c", "a$d", "b", "b$a", "b$a$1", "b$a$2", "c" ],
  "android.support.v4.c" : [ "a", "b", "b$a", "b$b", "c", "c$a", "d", "e", "f", "g", "g$1", "g$2", "g$a", "h" ],
  "android.support.v4.c.a" : [ "a", "b", "c", "c$a", "c$b", "d", "d$a", "e", "e$a", "f" ],
  "android.support.v4.d.a" : [ "a", "b", "c" ],
  "android.support.v4.e" : [ "a" ],
  "android.support.v4.f" : [ "a", "b", "b$a", "b$a$a", "c", "c$1", "c$a", "c$b", "d" ],
  "android.support.v4.g" : [ "a", "b", "b$1", "b$2", "b$3", "b$4", "b$a", "b$b", "b$c", "c", "c$1", "c$2", "c$2$1", "c$3", "c$a" ],
  "android.support.v4.h" : [ "a", "b", "c", "c$a", "c$b", "c$c", "c$d", "c$e", "c$f", "d" ],
  "android.support.v4.i" : [ "a", "a$1", "b", "b$1", "c", "d", "e", "f", "g", "h", "h$a", "h$b", "h$c", "h$d", "h$e", "i", "j", "k", "k$a", "k$b", "k$c", "l", "m", "n" ],
  "android.support.v4.j" : [ "a", "a$1", "a$2", "b", "b$a", "b$a$1", "b$b", "b$b$1", "c", "c$a", "c$b", "d", "e", "e$a", "e$b", "f", "g", "g$a", "g$b", "g$c", "h", "i", "j", "k", "l", "m", "n", "o", "p", "q", "q$a", "q$b", "q$c", "q$d", "q$e", "q$f", "q$f$1", "q$g", "q$h", "q$i", "q$j", "r", "s", "s$a", "s$b", "s$c", "t", "t$a", "t$b", "t$c", "u", "u$1", "u$2", "u$a", "v", "w", "x", "y" ],
  "android.support.v4.j.a" : [ "a", "b", "b$a", "b$b", "b$c", "c", "c$a", "c$b", "d" ],
  "android.support.v4.j.b" : [ "a", "b", "c", "d" ],
  "android.support.v4.media" : [ "MediaBrowserCompat", "MediaBrowserCompat$CustomActionResultReceiver", "MediaBrowserCompat$ItemReceiver", "MediaBrowserCompat$MediaItem", "MediaBrowserCompat$MediaItem$1", "MediaBrowserCompat$SearchResultReceiver", "MediaBrowserCompat$a", "MediaBrowserCompat$b", "MediaBrowserCompat$c", "MediaDescriptionCompat", "MediaDescriptionCompat$1", "MediaDescriptionCompat$a", "MediaMetadataCompat", "MediaMetadataCompat$1", "RatingCompat", "RatingCompat$1", "a", "a$a", "b", "b$a", "c" ],
  "android.support.v4.media.session" : [ "MediaControllerCompat", "MediaControllerCompat$MediaControllerImplApi21", "MediaControllerCompat$MediaControllerImplApi21$ExtraBinderRequestResultReceiver", "MediaControllerCompat$MediaControllerImplApi21$a", "MediaControllerCompat$a", "MediaControllerCompat$a$a", "MediaControllerCompat$a$b", "MediaControllerCompat$a$c", "MediaControllerCompat$b", "MediaSessionCompat", "MediaSessionCompat$QueueItem", "MediaSessionCompat$QueueItem$1", "MediaSessionCompat$ResultReceiverWrapper", "MediaSessionCompat$ResultReceiverWrapper$1", "MediaSessionCompat$Token", "MediaSessionCompat$Token$1", "ParcelableVolumeInfo", "ParcelableVolumeInfo$1", "PlaybackStateCompat", "PlaybackStateCompat$1", "PlaybackStateCompat$CustomAction", "PlaybackStateCompat$CustomAction$1", "a", "a$a", "a$a$a", "b", "b$a", "b$a$a", "c", "c$a", "c$b", "c$c", "d", "d$a", "e", "e$a", "f" ],
  "android.support.v4.widget" : [ "DrawerLayout", "DrawerLayout$1", "DrawerLayout$a", "DrawerLayout$b", "DrawerLayout$c", "DrawerLayout$d", "DrawerLayout$e", "DrawerLayout$e$1", "DrawerLayout$f", "DrawerLayout$f$1", "NestedScrollView", "NestedScrollView$a", "NestedScrollView$b", "NestedScrollView$c", "NestedScrollView$c$1", "Space", "a", "a$a", "a$b", "b", "c", "c$a", "c$b", "c$c", "d", "d$a", "d$b", "e", "e$a", "f", "f$a", "f$b", "g", "g$a", "g$b", "g$c", "h", "i", "j", "j$a", "j$b", "j$c", "j$d", "k", "l", "l$a", "l$b", "l$c", "l$d", "l$e", "l$f", "m", "n", "o", "o$1", "o$2", "o$a" ],
  "android.support.v7.a" : [ "a", "a$a", "a$b", "a$c", "a$d", "a$e", "a$f", "a$g", "a$h", "a$i", "a$j" ],
  "android.support.v7.app" : [ "AlertController", "AlertController$1", "AlertController$2", "AlertController$3", "AlertController$4", "AlertController$5", "AlertController$RecycleListView", "AlertController$a", "AlertController$a$1", "AlertController$a$2", "AlertController$a$3", "AlertController$a$4", "AlertController$a$a", "AlertController$b", "AlertController$c", "a", "a$a", "a$b", "a$c", "b", "b$1", "b$a", "b$b", "b$c", "b$d", "b$e", "c", "c$a", "d", "d$a", "e", "f", "g", "h", "h$1", "h$a", "h$b", "i", "i$a", "j", "k", "k$a", "k$b", "k$b$1", "l", "l$a", "m", "m$1", "m$2", "m$3", "m$4", "m$5", "m$5$1", "m$6", "m$a", "m$b", "m$b$1", "m$c", "m$d", "m$e", "n", "o", "o$a", "p", "q", "q$1", "q$2", "q$a", "q$b", "q$c", "r", "s", "s$a", "t", "t$1", "t$2", "t$3", "t$a" ],
  "android.support.v7.b.a" : [ "a", "b", "b$a", "c" ],
  "android.support.v7.c.a" : [ "a", "b" ],
  "android.support.v7.d" : [ "a", "a$a", "a$b" ],
  "android.support.v7.view" : [ "a", "b", "b$a", "c", "d", "e", "f", "f$a", "g", "g$a", "g$b", "h", "h$1", "i" ],
  "android.support.v7.view.menu" : [ "ActionMenuItemView", "ActionMenuItemView$a", "ActionMenuItemView$b", "ExpandedMenuView", "ListMenuItemView", "a", "b", "c", "d", "e", "e$1", "e$2", "e$3", "e$3$1", "e$a", "f", "f$a", "g", "h", "h$a", "h$b", "i", "j", "j$1", "k", "k$a", "k$b", "k$c", "k$d", "l", "l$a", "m", "n", "n$1", "o", "o$a", "p", "p$a", "q", "r", "s", "t", "t$1", "t$2", "u", "v" ],
  "android.support.v7.widget" : [ "ActionBarContainer", "ActionBarContextView", "ActionBarContextView$1", "ActionBarOverlayLayout", "ActionBarOverlayLayout$1", "ActionBarOverlayLayout$2", "ActionBarOverlayLayout$3", "ActionBarOverlayLayout$a", "ActionBarOverlayLayout$b", "ActionMenuView", "ActionMenuView$a", "ActionMenuView$b", "ActionMenuView$c", "ActionMenuView$d", "ActionMenuView$e", "ActivityChooserView", "ActivityChooserView$InnerLayout", "ActivityChooserView$a", "ActivityChooserView$b", "AlertDialogLayout", "ButtonBarLayout", "ContentFrameLayout", "ContentFrameLayout$a", "DialogTitle", "FitWindowsFrameLayout", "FitWindowsLinearLayout", "GridLayoutManager", "GridLayoutManager$a", "GridLayoutManager$b", "GridLayoutManager$c", "LinearLayoutManager", "LinearLayoutManager$a", "LinearLayoutManager$b", "LinearLayoutManager$c", "LinearLayoutManager$d", "LinearLayoutManager$d$1", "SearchView", "SearchView$SearchAutoComplete", "SearchView$SearchAutoComplete$1", "SearchView$a", "SearchView$b", "SearchView$c", "SearchView$d", "SearchView$e", "SearchView$e$1", "SearchView$f", "StaggeredGridLayoutManager", "StaggeredGridLayoutManager$1", "StaggeredGridLayoutManager$a", "StaggeredGridLayoutManager$b", "StaggeredGridLayoutManager$c", "StaggeredGridLayoutManager$c$a", "StaggeredGridLayoutManager$c$a$1", "StaggeredGridLayoutManager$d", "StaggeredGridLayoutManager$d$1", "StaggeredGridLayoutManager$e", "Toolbar", "Toolbar$1", "Toolbar$2", "Toolbar$3", "Toolbar$a", "Toolbar$b", "Toolbar$c", "Toolbar$d", "Toolbar$d$1", "ViewStubCompat", "ViewStubCompat$a", "a", "a$a", "aa", "aa$1", "ab", "ac", "ad", "ae", "ae$a", "ae$b", "af", "ag", "ah", "ah$1", "ah$2", "ah$3", "ah$4", "ah$5", "ah$6", "ah$7", "ah$8", "ah$a", "ah$b", "ai", "aj", "ak", "ak$1", "ak$2", "ak$a", "ak$b", "al", "al$a", "am", "am$a", "am$b", "an", "an$1", "an$a", "an$b", "ao", "ap", "ap$a", "aq", "aq$1", "aq$2", "aq$a", "aq$b", "aq$c", "aq$d", "aq$e", "ar", "ar$a", "as", "at", "at$a", "au", "au$a", "av", "av$1", "av$2", "aw", "aw$1", "aw$2", "aw$3", "aw$4", "aw$5", "aw$6", "aw$a", "aw$b", "aw$c", "aw$d", "aw$e", "aw$e$a", "aw$e$b", "aw$e$c", "aw$f", "aw$g", "aw$h", "aw$h$1", "aw$h$2", "aw$h$a", "aw$h$b", "aw$i", "aw$j", "aw$k", "aw$l", "aw$m", "aw$n", "aw$n$a", "aw$o", "aw$p", "aw$q", "aw$r", "aw$r$1", "aw$s", "aw$s$a", "aw$t", "aw$u", "aw$v", "aw$w", "ax", "ax$a", "ay", "az", "b", "ba", "bb", "bb$1", "bb$a", "bb$b", "bb$c", "bc", "bd", "bd$a", "be", "bf", "bg", "bh", "bi", "bj", "bk", "bk$1", "bk$2", "bl", "bl$1", "bl$a", "bl$b", "bl$c", "bm", "bm$1", "bm$2", "bn", "bo", "bp", "bp$a", "bp$b", "bq", "bq$a", "bq$b", "br", "bs", "c", "d", "d$a", "d$b", "d$c", "d$d", "d$d$1", "d$e", "d$f", "e", "e$a", "e$b", "e$c", "e$d", "e$e", "f", "f$a", "f$b", "g", "h", "i", "j", "k", "l", "m", "m$a", "m$b", "m$c", "m$d", "n", "o", "p", "q", "r", "s", "t", "u", "v", "w", "x", "y", "z", "z$1", "z$a", "z$b", "z$b$1", "z$b$2", "z$b$3" ],
  "com.basgeekball.awesomevalidation" : [ "AwesomeValidation", "AwesomeValidation$1", "BuildConfig", "R", "R$anim", "R$animator", "R$attr", "R$bool", "R$color", "R$dimen", "R$drawable", "R$id", "R$integer", "R$layout", "R$string", "R$style", "R$styleable", "ValidationHolder", "ValidationStyle" ],
  "com.basgeekball.awesomevalidation.demo" : [ "BuildConfig", "DemoActivity", "DemoActivity$1", "DemoActivity$2", "DemoActivity$3", "DemoActivity$4", "DemoActivity$5", "DemoActivity$6", "DemoActivity$7", "DemoActivity$DrawerItemClickListener", "NameFragment", "PasswordFragment", "R", "R$anim", "R$animator", "R$array", "R$attr", "R$bool", "R$color", "R$dimen", "R$drawable", "R$id", "R$integer", "R$layout", "R$string", "R$style", "R$styleable" ],
  "com.basgeekball.awesomevalidation.exception" : [ "BadLayoutException", "MissingContextException", "UnsupportedLayoutException" ],
  "com.basgeekball.awesomevalidation.helper" : [ "RangeHelper", "SpanHelper" ],
  "com.basgeekball.awesomevalidation.model" : [ "NumericRange" ],
  "com.basgeekball.awesomevalidation.utility" : [ "RegexTemplate", "ValidationCallback", "ViewsInfo" ],
  "com.basgeekball.awesomevalidation.utility.custom" : [ "CustomErrorReset", "CustomValidation", "CustomValidationCallback", "SimpleCustomValidation" ],
  "com.basgeekball.awesomevalidation.validators" : [ "BasicValidator", "BasicValidator$1", "ColorationValidator", "ColorationValidator$1", "ColorationValidator$1$1", "TextInputLayoutValidator", "TextInputLayoutValidator$1", "UnderlabelValidator", "UnderlabelValidator$1", "UnderlabelValidator$2", "Validator" ],
  "com.google.common.a" : [ "a", "a$1", "b" ],
  "com.google.common.annotations" : [ "Beta", "GwtCompatible", "GwtIncompatible", "VisibleForTesting" ],
  "com.google.common.b" : [ "a", "b" ],
  "com.google.common.base" : [ "Ascii", "CaseFormat", "CaseFormat$1", "CaseFormat$2", "CaseFormat$3", "CaseFormat$4", "CaseFormat$5", "CaseFormat$a", "CharMatcher", "CharMatcher$1", "CharMatcher$a", "CharMatcher$aa", "CharMatcher$ab", "CharMatcher$b", "CharMatcher$c", "CharMatcher$d", "CharMatcher$e", "CharMatcher$f", "CharMatcher$g", "CharMatcher$h", "CharMatcher$i", "CharMatcher$j", "CharMatcher$k", "CharMatcher$l", "CharMatcher$m", "CharMatcher$n", "CharMatcher$o", "CharMatcher$p", "CharMatcher$q", "CharMatcher$r", "CharMatcher$s", "CharMatcher$t", "CharMatcher$u", "CharMatcher$v", "CharMatcher$w", "CharMatcher$x", "CharMatcher$y", "CharMatcher$z", "Charsets", "Converter", "Converter$1", "Converter$1$1", "Converter$a", "Converter$b", "Converter$c", "Converter$d", "Defaults", "Enums", "Enums$a", "Equivalence", "Equivalence$1", "Equivalence$Wrapper", "Equivalence$a", "Equivalence$b", "Equivalence$c", "FinalizablePhantomReference", "FinalizableReference", "FinalizableReferenceQueue", "FinalizableReferenceQueue$a", "FinalizableReferenceQueue$b", "FinalizableReferenceQueue$c", "FinalizableReferenceQueue$d", "FinalizableSoftReference", "FinalizableWeakReference", "Function", "Functions", "Functions$1", "Functions$a", "Functions$b", "Functions$c", "Functions$d", "Functions$e", "Functions$f", "Functions$g", "Functions$h", "Joiner", "Joiner$1", "Joiner$2", "Joiner$3", "Joiner$MapJoiner", "MoreObjects", "MoreObjects$1", "MoreObjects$ToStringHelper", "MoreObjects$ToStringHelper$a", "Objects", "Optional", "Optional$1", "Optional$1$1", "Preconditions", "Predicate", "Predicates", "Predicates$1", "Predicates$a", "Predicates$b", "Predicates$c", "Predicates$d", "Predicates$e", "Predicates$f", "Predicates$g", "Predicates$h", "Predicates$i", "Predicates$i$1", "Predicates$i$2", "Predicates$i$3", "Predicates$i$4", "Predicates$j", "Predicates$k", "Splitter", "Splitter$1", "Splitter$1$1", "Splitter$2", "Splitter$2$1", "Splitter$3", "Splitter$3$1", "Splitter$4", "Splitter$4$1", "Splitter$5", "Splitter$MapSplitter", "Splitter$a", "Splitter$b", "StandardSystemProperty", "Stopwatch", "Stopwatch$1", "Strings", "Supplier", "Suppliers", "Suppliers$a", "Suppliers$b", "Suppliers$c", "Suppliers$d", "Suppliers$e", "Suppliers$f", "Suppliers$g", "Suppliers$h", "Throwables", "Throwables$1", "Ticker", "Ticker$1", "Utf8", "Verify", "VerifyException", "a", "b", "b$1", "b$a", "c", "d", "e", "f", "g", "g$a", "h", "i", "j", "j$1", "j$a", "k", "l" ],
  "com.google.common.base.internal" : [ "Finalizer" ],
  "com.google.common.collect" : [ "Range", "Range$1", "Range$a", "Range$b", "Range$c", "a", "aa", "ab", "ac", "ad", "ad$a", "ad$b", "ad$c", "ae", "af", "ag", "ah", "ah$a", "ah$a$1", "ah$b", "ah$c", "ai", "aj", "ak", "al", "am", "an", "ao", "ap", "b", "c", "d", "e", "f", "g", "h", "i", "i$1", "i$a", "j", "k", "k$a", "k$b", "k$c", "k$d", "l", "m", "n", "o", "o$a", "o$b", "p", "p$a", "p$b", "p$c", "q", "q$a", "r", "s", "t", "u", "v", "v$a", "w", "x", "x$1", "x$a", "x$aa", "x$ab", "x$b", "x$c", "x$d", "x$e", "x$f", "x$g", "x$h", "x$i", "x$j", "x$k", "x$l", "x$m", "x$m$1", "x$m$2", "x$n", "x$n$a", "x$o", "x$p", "x$p$a", "x$q", "x$r", "x$s", "x$t", "x$u", "x$u$a", "x$v", "x$w", "x$w$a", "x$x", "x$y", "x$z", "y", "y$1", "y$a", "y$a$1", "y$a$2", "z" ]
}